config/config.yml
telegram_download_chat/__init__.py
telegram_download_chat/__main__.py
telegram_download_chat/core.py
telegram_download_chat/partial.py
telegram_download_chat/paths.py
telegram_download_chat/cli/__init__.py
telegram_download_chat/cli/arguments.py
telegram_download_chat/cli/commands.py
telegram_download_chat/core/__init__.py
telegram_download_chat/core/auth.py
telegram_download_chat/core/auth_utils.py
telegram_download_chat/core/config.py
telegram_download_chat/core/context.py
telegram_download_chat/core/download.py
telegram_download_chat/core/downloader.py
telegram_download_chat/core/entities.py
telegram_download_chat/core/messages.py
telegram_download_chat/core/presets.py
telegram_download_chat/gui/TODO.md
telegram_download_chat/gui/__init__.py
telegram_download_chat/gui/main.py
telegram_download_chat/gui/worker.py
telegram_download_chat/gui/auth/__init__.py
telegram_download_chat/gui/auth/session_manager.py
telegram_download_chat/gui/tabs/__init__.py
telegram_download_chat/gui/tabs/convert_tab.py
telegram_download_chat/gui/tabs/download_tab.py
telegram_download_chat/gui/tabs/settings_tab.py
telegram_download_chat/gui/utils/__init__.py
telegram_download_chat/gui/utils/config.py
telegram_download_chat/gui/utils/file_utils.py
telegram_download_chat/gui/widgets/__init__.py
telegram_download_chat/gui/widgets/file_list.py
telegram_download_chat/gui/widgets/log_viewer.py
telegram_download_chat/gui/windows/__init__.py
telegram_download_chat/gui/windows/main_window.py
telegram_download_chat/web/__init__.py
telegram_download_chat/web/main.py
telegram_download_chat-0.5.4.dist-info/METADATA
telegram_download_chat-0.5.4.dist-info/WHEEL
telegram_download_chat-0.5.4.dist-info/entry_points.txt
telegram_download_chat-0.5.4.dist-info/top_level.txt
telegram_download_chat-0.5.4.dist-info/RECORD
