Metadata-Version: 2.4
Name: telegram-download-chat
Version: 0.5.4
Summary: CLI utility for downloading Telegram chat history to JSON
Home-page: https://github.com/popstas/telegram-download-chat
Author: Stanislav Popov
Author-email: Stanislav Popov <popstas@gmail.com>
License: MIT
Project-URL: Homepage, https://github.com/popstas/telegram-download-chat
Project-URL: Bug-Tracker, https://github.com/popstas/telegram-download-chat/issues
Classifier: Development Status :: 4 - Beta
Classifier: Intended Audience :: End Users/Desktop
Classifier: License :: OSI Approved :: MIT License
Classifier: Programming Language :: Python :: 3
Classifier: Programming Language :: Python :: 3.8
Classifier: Programming Language :: Python :: 3.9
Classifier: Programming Language :: Python :: 3.10
Classifier: Programming Language :: Python :: 3.11
Classifier: Programming Language :: Python :: 3.12
Classifier: Topic :: Communications :: Chat
Classifier: Topic :: Utilities
Requires-Python: >=3.8
Requires-Dist: telethon>=1.34.0
Requires-Dist: PyYAML>=6.0.0
Requires-Dist: pyinstaller>=6.0.0
Requires-Dist: setuptools<81.0.0
Provides-Extra: gui
Requires-Dist: PySide6>=6.5.0; extra == "gui"
Provides-Extra: web
Requires-Dist: streamlit>=1.30.0; extra == "web"
Provides-Extra: dev
Requires-Dist: pytest>=6.0; extra == "dev"
Requires-Dist: pytest-asyncio>=0.21; extra == "dev"
Requires-Dist: pytest-cov>=4.0; extra == "dev"
Requires-Dist: black>=22.0; extra == "dev"
Requires-Dist: isort>=5.10.0; extra == "dev"
Requires-Dist: mypy>=0.910; extra == "dev"
Requires-Dist: flake8>=4.0.0; extra == "dev"
Dynamic: author
Dynamic: home-page
Dynamic: requires-python
